Metadata-Version: 1.1
Name: testreport
Version: 0.1.1
Summary: Test Report - Generate reports based on test cases
Home-page: https://github.com/cristianowa/testreport
Author: Cristiano W. Araujo
Author-email: cristianowerneraraujo@gmail.com
License: UNKNOWN
Download-URL: https://github.com/cristianowa/testreport/archive/0.1.zip
Keywords: dictionary
Platform: UNKNOWN
